sc2rl/__init__.py
sc2rl/environments/EnvironmentBase.py
sc2rl/environments/MicroTestEnvironment.py
sc2rl/environments/SC2BotAI.py
sc2rl/environments/__init__.py
sc2rl/utils/__init__.py
sc2rl/utils/sc2_utils.py
sc2rl-0.0.2.dist-info/METADATA
sc2rl-0.0.2.dist-info/WHEEL
sc2rl-0.0.2.dist-info/top_level.txt
sc2rl-0.0.2.dist-info/RECORD
